countries_kh/__init__.py
countries_kh/country_list.py
countries_kh-0.1.dist-info/METADATA
countries_kh-0.1.dist-info/WHEEL
countries_kh-0.1.dist-info/top_level.txt
countries_kh-0.1.dist-info/RECORD
