Metadata-Version: 2.1
Name: countries_kh
Version: 0.1
Summary: A package to get Ids of countries
Author: Bharath Reddy
Classifier: Programming Language :: Python :: 3
Classifier: License :: OSI Approved :: MIT License
Classifier: Operating System :: OS Independent
